mri_distortion_toolkit/DistortionCorrection.py
mri_distortion_toolkit/FieldCalculation.py
mri_distortion_toolkit/Harmonics.py
mri_distortion_toolkit/MarkerAnalysis.py
mri_distortion_toolkit/PhantomDesigner.py
mri_distortion_toolkit/Reports.py
mri_distortion_toolkit/__init__.py
mri_distortion_toolkit/calculate_harmonics.py
mri_distortion_toolkit/utilities.py
mri_distortion_toolkit/jinja_templates/MR_report.html
mri_distortion_toolkit/jinja_templates/themes/README.md
mri_distortion_toolkit/jinja_templates/themes/d42ker-github.css
mri_distortion_toolkit/jinja_templates/themes/whitey.css
mri_distortion_toolkit-0.14.10.dist-info/METADATA
mri_distortion_toolkit-0.14.10.dist-info/WHEEL
mri_distortion_toolkit-0.14.10.dist-info/top_level.txt
mri_distortion_toolkit-0.14.10.dist-info/RECORD
