Metadata-Version: 2.1
Name: mri_distortion_toolkit
Version: 0.14.10
Summary: Quality assurance tools for MRI geometric distortion
Home-page: https://image-x-institute.github.io/mri_distortion_toolkit/index.html
Author: Brendan Whelan, Paul Liu, Shanshan Shan
Author-email: bwheelz360@gmail.com
Project-URL: Bug Tracker, https://github.com/Image-X-Institute/mri_distortion_toolkit
Classifier: Programming Language :: Python :: 3
Classifier: License :: OSI Approved :: GNU General Public License v3 (GPLv3)
Requires-Python: >=3.8
Requires-Dist: numpy
Requires-Dist: scipy
Requires-Dist: scikit-image
Requires-Dist: matplotlib
Requires-Dist: pydicom
Requires-Dist: pandas
Requires-Dist: seaborn
Requires-Dist: plotly
Requires-Dist: jinja2
Requires-Dist: finufft
Requires-Dist: get-all-files
